{"main/tabs/dashboard":{"isFragment":true,"asStarter":false,"needLogin":false,"pageUrl":"main/tabs/dashboard","clazName":"com.zz.ppjoke.ui.dashboard.DashboardFragment","id":1190269506},"main/tabs/home":{"isFragment":true,"asStarter":true,"needLogin":false,"pageUrl":"main/tabs/home","clazName":"com.zz.ppjoke.ui.home.HomeFragment","id":1426314286},"main/tabs/notification":{"isFragment":true,"asStarter":false,"needLogin":false,"pageUrl":"main/tabs/notification","clazName":"com.zz.ppjoke.ui.notifications.NotificationsFragment","id":1086549914}}